[{
        "result": {
            "detailedDescription": {
                "license": "https:\/\/en.wikipedia.org\/wiki\/Wikipedia:Text_of_Creative_Commons_Attribution-ShareAlike_3.0_Unported_License",
                "articleBody": "Pinkafeld Airport is a private use airport located 2 kilometres north-northwest of Pinkafeld, Burgenland, Austria.",
                "url": "http:\/\/en.wikipedia.org\/wiki\/Pinkafeld_Airport"
            },
            "@type": ["Airport", "Place", "Thing"],
            "name": "Pinkafeld Airport",
            "description": "Airport",
            "@id": "kg:\/m\/0wktn6_"
        },
        "@type": "EntitySearchResult",
        "resultScore": 10.497664
    }]
